[{"id":"M2rJ2Mdp3Z_aBeY-k6PEC","title":"prueba 1","description":"a","price":1,"thumbnail":["https://i.blogs.es/0ca9a6/aa/1366_2000.jpeg","https://i.blogs.es/0ca9a6/aa/1366_2000.jpeg"],"code":"1","stock":2,"category":"a"},{"id":"YLpZrsReuYPrS5K9Zv0qx","title":"prueba 2","description":"b","price":1,"thumbnail":["https://i.blogs.es/0ca9a6/aa/1366_2000.jpeg","https://i.blogs.es/0ca9a6/aa/1366_2000.jpeg"],"code":"2","stock":2,"category":"b"},{"id":"Qlo960vYqbIKhvv3g0sWp","title":"prueba 2.1","description":"ab","price":1,"thumbnail":["https://i.blogs.es/0ca9a6/aa/1366_2000.jpeg","https://i.blogs.es/0ca9a6/aa/1366_2000.jpeg"],"code":"2.1","stock":2,"category":"ab"},{"id":"fDdDRy-_5OynkSVipE9Sp","title":"prueba 2.1","description":"ab","price":1,"thumbnail":["https://i.blogs.es/0ca9a6/aa/1366_2000.jpeg","https://i.blogs.es/0ca9a6/aa/1366_2000.jpeg"],"code":"2.c1","stock":2,"category":"abc"}]